<?xml version="1.0" encoding="UTF-8"?>
<persistence version="2.0" xmlns="http://java.sun.com/xml/ns/persistence" xmlns:xsi="http://www.w3.org/2001/XMLSchema-instance" xsi:schemaLocation="http://java.sun.com/xml/ns/persistence http://java.sun.com/xml/ns/persistence/persistence_2_0.xsd">
	<persistence-unit name="HelloJSF" transaction-type="RESOURCE_LOCAL">
		<class>modelo.PessoaJPA</class>
		<properties>
			<property name="javax.persistence.jdbc.driver" value="com.mysql.jdbc.Driver"/>
			<property name="javax.persistence.jdbc.url" value="jdbc:mysql://localhost:3306/mydb?relaxAutoCommit=true"/>
			<property name="javax.persistence.jdbc.user" value="root"/>
			<property name="javax.persistence.jdbc.password" value="masterkey"/>
			<property name="hibernate.dialect" value="org.hibernate.dialect.MySQLInnoDBDialect"/>
			<property name="hibernate.connection.driver_class" value="org.gjt.mm.mysql.Driver"/>
			<property name="hibernate.connection.url" value="jdbc:mysql://localhost/mydb"/>
			<property name="hibernate.connection.username" value="root"/>
			<property name="hibernate.connection.password" value="masterkey"/>
		</properties>
	</persistence-unit>
</persistence>
